<?xml version='1.0' encoding='ISO-8859-1' standalone='yes' ?>
	<help>
		<element name="DESCRIPTION" text="Este algoritmo elimina valores de todas aquellas clases con un &#225;rea menor que un umbral dado. Todas aquellas celdas que no formen parte de un conjunto agregado (conjunto de celdas contiguas con el mismo valor) de tama&#241;o mayor que el umbral ser&#225;n sustituidas por el valor de sin datos." description="Descripci&#243;n" type="0">
		</element>
		<element name="ADDITIONAL_INFO" text="" description="Informaci&#243;n adicional" type="0">
		</element>
		<element name="EXTENSION_AUTHOR" description="Algoritmo creado por" text="Victor Olaya" type="0">
		</element>
		<element name="HELP_AUTHOR" text="Victor Olaya y Antonio Ordoñez" description="Ayuda creada por" type="0">
		</element>
		<element name="USER_NOTES" text="" description="Notas de usuario" type="0">
		</element>
		<element name="INPUT" text="la capa de clases de partida." description="Capa de clases" type="3">
		</element>
		<element name="MINAREA" text="&#225;rea m&#237;nima en n&#250;mero de celdas." description="&#193;rea m&#237;nima(celdas)" type="3">
		</element>
		<element name="OUTPUT_DESCRIPTION" text="" description="Descripci&#243;n general" type="2">
		</element>
		<element name="RESULT" text="" description="Capa filtrada" type="2">
		</element>
	</help>
<?xml version='1.0' encoding='ISO-8859-1' standalone='yes' ?>