<?xml version='1.0' encoding='ISO-8859-1' standalone='yes' ?>
	<help>
		<element name="DESCRIPTION" text="Obtiene una nueva capa de informaci&#243;n raster a partir de la capa de entrada, con una menor resoluci&#243;n. Al especificar el tama&#241;o de agregaci&#243;n que se quiere aplicar, la extensi&#243;n determina la resoluci&#243;n del raster de salida multiplicando el tama&#241;o de celda de la capa origen.&#10;&#10;Debe emplearse esta extension en los casos en que no sea correcto emplear un simple remuestreo, por ejemplo si la variable expresada en las celdas es un conteo (ver figura inferior)." description="Descripci&#243;n" type="0">
			<image description="Dependiendo de la variable recogida en la capa, el proceso de remuestreo puede requerir operaciones adicionales para obtener un resultado correcto. a) capa con valores de conteos (n&#250;mero de individuos) por celda para una especie dada, b) capa tras remuestreo (incorrecta), c) capa tras remuestreo y aplicaci&#243;n de factor de reescala (correcta)." file="agregar.jpg">
			</image>
		</element>
		<element name="ADDITIONAL_INFO" text="" description="Informaci&#243;n adicional" type="0">
		</element>
		<element name="EXTENSION_AUTHOR" description="Algoritmo creado por" text="Victor Olaya" type="0">
		</element>
		<element name="HELP_AUTHOR" text="Victor Olaya y Antonio Ordoñez" description="Ayuda creada por" type="0">
		</element>
		<element name="USER_NOTES" text="" description="Notas de usuario" type="0">
		</element>
		<element name="GRID" text="capa de entrada." description="Capa origen" type="3">
		</element>
		<element name="METHOD" text="el m&#233;todo a utilizar, a elegir entre los siguientes:&#10;* Suma&#10;* M&#225;ximo&#10;* M&#237;nimo&#10; " description="M&#233;todo" type="3">
		</element>
		<element name="SIZE" text="Un valor entero que que relaciona los tama&#241;os de celda. Un factor de 2 implica que la capa resultante tendra un tama&#241;o de celda el doble que la de entrada." description="Tama&#241;o de agregaci&#243;n" type="3">
		</element>
		<element name="OUTPUT_DESCRIPTION" text="" description="Descripci&#243;n general" type="2">
		</element>
		<element name="RESULT" text="nueva capa de informaci&#243;n raster a partir de la capa de entrada con una menor resoluci&#243;n espacial.&#10;&#10;" description="Capa agregada" type="2">
		</element>
	</help>
<?xml version='1.0' encoding='ISO-8859-1' standalone='yes' ?>